odoo/addons/partner_exception/__init__.py
odoo/addons/partner_exception/__manifest__.py
odoo/addons/partner_exception/i18n/partner_exception.pot
odoo/addons/partner_exception/models/__init__.py
odoo/addons/partner_exception/models/res_partner.py
odoo/addons/partner_exception/static/description/icon.png
odoo/addons/partner_exception/views/contact_views.xml
odoo13_addon_partner_exception-13.0.1.0.1.dist-info/METADATA
odoo13_addon_partner_exception-13.0.1.0.1.dist-info/WHEEL
odoo13_addon_partner_exception-13.0.1.0.1.dist-info/top_level.txt
odoo13_addon_partner_exception-13.0.1.0.1.dist-info/RECORD
